docker_files_generator/__init__.py
docker_files_generator/main.py
docker_chatgpt_files_generator-0.1.2.dist-info/LICENSE
docker_chatgpt_files_generator-0.1.2.dist-info/METADATA
docker_chatgpt_files_generator-0.1.2.dist-info/WHEEL
docker_chatgpt_files_generator-0.1.2.dist-info/top_level.txt
docker_chatgpt_files_generator-0.1.2.dist-info/RECORD
